gvitest_script/__init__.py
gvitest_script/core/__init__.py
gvitest_script/core/control_flow_processor.py
gvitest_script/core/error_handler.py
gvitest_script/core/script_generator.py
gvitest_script/core/template_engine.py
gvitest_script/demos/__init__.py
gvitest_script/demos/demo.py
gvitest_script/demos/script_server.log
gvitest_script/demos/websocket_demo.py
gvitest_script/models/__init__.py
gvitest_script/models/api_models.py
gvitest_script/models/can_models.py
gvitest_script/models/checkpoint.py
gvitest_script/models/config_models.py
gvitest_script/models/control_flow_models.py
gvitest_script/models/expected_result.py
gvitest_script/models/image_processing_config.py
gvitest_script/models/logging_config.py
gvitest_script/models/real_time_tracking_config.py
gvitest_script/models/script_context.py
gvitest_script/models/validation_model.py
gvitest_script/script_server.log
gvitest_script/service/__init__.py
gvitest_script/service/log_query.py
gvitest_script/service/script.py
gvitest_script/service/status_tracking.py
gvitest_script/service/websocket_server.py
gvitest_script/templates/base/can_utils.j2
gvitest_script/templates/base/expression_utils.j2
gvitest_script/templates/base/image_utils.j2
gvitest_script/templates/base/imports.j2
gvitest_script/templates/base/logging_setup.j2
gvitest_script/templates/base/real_time_tracking.j2
gvitest_script/templates/base/status_tracking.j2
gvitest_script/templates/base/utilities.j2
gvitest_script/templates/base/validation_utils.j2
gvitest_script/templates/handlers/can_handler.j2
gvitest_script/templates/handlers/click_handler.j2
gvitest_script/templates/handlers/control_flow_handler.j2
gvitest_script/templates/handlers/default_handler.j2
gvitest_script/templates/handlers/error_handler.j2
gvitest_script/templates/handlers/scroll_handler.j2
gvitest_script/templates/handlers/swipe_handler.j2
gvitest_script/templates/handlers/type_handler.j2
gvitest_script/templates/main/action_dispatcher.j2
gvitest_script-0.1.5.dist-info/WHEEL
gvitest_script-0.1.5.dist-info/METADATA
gvitest_script-0.1.5.dist-info/RECORD
